{
    "dailyPrayers": [
        {
            "responseCode": null,
            "responseDesc": null,
            "fajrHour": 4,
            "fajrMinute": 45,
            "dhuhrHour": 13,
            "dhuhrMinute": 39,
            "asrHour": 18,
            "asrMinute": 18,
            "maghribHour": 20,
            "maghribMinute": 28,
            "ishaHour": 21,
            "ishaMinute": 48,
            "qiyamHour": 1,
            "qiyamMinute": 58,
            "hijriDay": 13,
            "hijriMonth": 1,
            "hijriYear": 1442,
            "hijriDayOfWeek": 0,
            "hiriMonthName": "Muharram",
            "hijriMonthNameEnglish": "Muharram",
            "hijriDate": "13th Muharram, 1442h",
            "sunriseHour": 0,
            "sunriseMinute": 0,
            "gregorianDate": 1598971800000,
            "gregorianDay": 1,
            "gregorianMonth": 8,
            "gregorianMonthName": "September",
            "gregorianMonthNameEnglish": "September",
            "gregorianYear": 2020,
            "gregorianDateString": "Sep 01, 2020",
            "dayOfWeek": "Tue",
            "nextPrayer": "lang.asr",
            "nextPrayerRemainingTime": "3:28:59",
            "nextPrayerRemainingTimeHours": 3,
            "nextPrayerRemainingTimeMinutes": 28,
            "nextPrayerRemainingTimeinDateFormat": 1598844480000,
            "currentPrayer": "lang.dhuhar",
            "currentPrayerPassedTime": "1 hour(s) 11 minute(s) ago",
            "currentPrayerPassedTimeHours": 1,
            "currentPrayerPassedTimeMinutes": 11,
            "islamicEvent": null,
            "fajarTime": "04:45 AM",
            "sunriseTime": "06:50 AM",
            "dhuharTime": "01:39 PM",
            "asrTime": "06:18 PM",
            "maghribTime": "08:28 PM",
            "ishaTime": "09:48 PM",
            "qiyamTime": "01:58 AM",
            "isToday": 0,
            "fajarJamahTime": "5:45 AM",
            "zohrJamahTime": "2:00 PM",
            "asarJamahTime": "7:30 PM",
            "magribJamahTime": "8:33 PM",
            "ishaJamahTime": "10:10 PM"
        },
        {
            "responseCode": null,
            "responseDesc": null,
            "fajrHour": 4,
            "fajrMinute": 48,
            "dhuhrHour": 13,
            "dhuhrMinute": 39,
            "asrHour": 18,
            "asrMinute": 16,
            "maghribHour": 20,
            "maghribMinute": 26,
            "ishaHour": 21,
            "ishaMinute": 46,
            "qiyamHour": 2,
            "qiyamMinute": 0,
            "hijriDay": 14,
            "hijriMonth": 1,
            "hijriYear": 1442,
            "hijriDayOfWeek": 0,
            "hiriMonthName": "Muharram",
            "hijriMonthNameEnglish": "Muharram",
            "hijriDate": "14th Muharram, 1442h",
            "sunriseHour": 0,
            "sunriseMinute": 0,
            "gregorianDate": 1599058200000,
            "gregorianDay": 2,
            "gregorianMonth": 8,
            "gregorianMonthName": "September",
            "gregorianMonthNameEnglish": "September",
            "gregorianYear": 2020,
            "gregorianDateString": "Sep 02, 2020",
            "dayOfWeek": "Wed",
            "nextPrayer": "lang.asr",
            "nextPrayerRemainingTime": "3:26:59",
            "nextPrayerRemainingTimeHours": 3,
            "nextPrayerRemainingTimeMinutes": 26,
            "nextPrayerRemainingTimeinDateFormat": 1598844360000,
            "currentPrayer": "lang.dhuhar",
            "currentPrayerPassedTime": "1 hour(s) 11 minute(s) ago",
            "currentPrayerPassedTimeHours": 1,
            "currentPrayerPassedTimeMinutes": 11,
            "islamicEvent": null,
            "fajarTime": "04:48 AM",
            "sunriseTime": "06:52 AM",
            "dhuharTime": "01:39 PM",
            "asrTime": "06:16 PM",
            "maghribTime": "08:26 PM",
            "ishaTime": "09:46 PM",
            "qiyamTime": "02:00 AM",
            "isToday": 0,
            "fajarJamahTime": "5:45 AM",
            "zohrJamahTime": "2:00 PM",
            "asarJamahTime": "7:30 PM",
            "magribJamahTime": "8:31 PM",
            "ishaJamahTime": "10:10 PM"
        },
        {
            "responseCode": null,
            "responseDesc": null,
            "fajrHour": 4,
            "fajrMinute": 50,
            "dhuhrHour": 13,
            "dhuhrMinute": 39,
            "asrHour": 18,
            "asrMinute": 14,
            "maghribHour": 20,
            "maghribMinute": 23,
            "ishaHour": 21,
            "ishaMinute": 43,
            "qiyamHour": 2,
            "qiyamMinute": 1,
            "hijriDay": 15,
            "hijriMonth": 1,
            "hijriYear": 1442,
            "hijriDayOfWeek": 0,
            "hiriMonthName": "Muharram",
            "hijriMonthNameEnglish": "Muharram",
            "hijriDate": "15th Muharram, 1442h",
            "sunriseHour": 0,
            "sunriseMinute": 0,
            "gregorianDate": 1599144600000,
            "gregorianDay": 3,
            "gregorianMonth": 8,
            "gregorianMonthName": "September",
            "gregorianMonthNameEnglish": "September",
            "gregorianYear": 2020,
            "gregorianDateString": "Sep 03, 2020",
            "dayOfWeek": "Thu",
            "nextPrayer": "lang.asr",
            "nextPrayerRemainingTime": "3:24:59",
            "nextPrayerRemainingTimeHours": 3,
            "nextPrayerRemainingTimeMinutes": 24,
            "nextPrayerRemainingTimeinDateFormat": 1598844240000,
            "currentPrayer": "lang.dhuhar",
            "currentPrayerPassedTime": "1 hour(s) 11 minute(s) ago",
            "currentPrayerPassedTimeHours": 1,
            "currentPrayerPassedTimeMinutes": 11,
            "islamicEvent": null,
            "fajarTime": "04:50 AM",
            "sunriseTime": "06:54 AM",
            "dhuharTime": "01:39 PM",
            "asrTime": "06:14 PM",
            "maghribTime": "08:23 PM",
            "ishaTime": "09:43 PM",
            "qiyamTime": "02:01 AM",
            "isToday": 0,
            "fajarJamahTime": "5:45 AM",
            "zohrJamahTime": "2:00 PM",
            "asarJamahTime": "7:30 PM",
            "magribJamahTime": "8:28 PM",
            "ishaJamahTime": "10:10 PM"
        },
        {
            "responseCode": null,
            "responseDesc": null,
            "fajrHour": 4,
            "fajrMinute": 53,
            "dhuhrHour": 13,
            "dhuhrMinute": 38,
            "asrHour": 18,
            "asrMinute": 13,
            "maghribHour": 20,
            "maghribMinute": 21,
            "ishaHour": 21,
            "ishaMinute": 41,
            "qiyamHour": 2,
            "qiyamMinute": 1,
            "hijriDay": 16,
            "hijriMonth": 1,
            "hijriYear": 1442,
            "hijriDayOfWeek": 0,
            "hiriMonthName": "Muharram",
            "hijriMonthNameEnglish": "Muharram",
            "hijriDate": "16th Muharram, 1442h",
            "sunriseHour": 0,
            "sunriseMinute": 0,
            "gregorianDate": 1599231000000,
            "gregorianDay": 4,
            "gregorianMonth": 8,
            "gregorianMonthName": "September",
            "gregorianMonthNameEnglish": "September",
            "gregorianYear": 2020,
            "gregorianDateString": "Sep 04, 2020",
            "dayOfWeek": "Fri",
            "nextPrayer": "lang.asr",
            "nextPrayerRemainingTime": "3:23:59",
            "nextPrayerRemainingTimeHours": 3,
            "nextPrayerRemainingTimeMinutes": 23,
            "nextPrayerRemainingTimeinDateFormat": 1598844180000,
            "currentPrayer": "lang.dhuhar",
            "currentPrayerPassedTime": "1 hour(s) 12 minute(s) ago",
            "currentPrayerPassedTimeHours": 1,
            "currentPrayerPassedTimeMinutes": 12,
            "islamicEvent": null,
            "fajarTime": "04:53 AM",
            "sunriseTime": "06:55 AM",
            "dhuharTime": "01:38 PM",
            "asrTime": "06:13 PM",
            "maghribTime": "08:21 PM",
            "ishaTime": "09:41 PM",
            "qiyamTime": "02:01 AM",
            "isToday": 0,
            "fajarJamahTime": "6:00 AM",
            "zohrJamahTime": "2:00 PM",
            "asarJamahTime": "7:00 PM",
            "magribJamahTime": "8:26 PM",
            "ishaJamahTime": "10:00 PM"
        },
        {
            "responseCode": null,
            "responseDesc": null,
            "fajrHour": 4,
            "fajrMinute": 55,
            "dhuhrHour": 13,
            "dhuhrMinute": 38,
            "asrHour": 18,
            "asrMinute": 11,
            "maghribHour": 20,
            "maghribMinute": 19,
            "ishaHour": 21,
            "ishaMinute": 39,
            "qiyamHour": 2,
            "qiyamMinute": 3,
            "hijriDay": 17,
            "hijriMonth": 1,
            "hijriYear": 1442,
            "hijriDayOfWeek": 0,
            "hiriMonthName": "Muharram",
            "hijriMonthNameEnglish": "Muharram",
            "hijriDate": "17th Muharram, 1442h",
            "sunriseHour": 0,
            "sunriseMinute": 0,
            "gregorianDate": 1599317400000,
            "gregorianDay": 5,
            "gregorianMonth": 8,
            "gregorianMonthName": "September",
            "gregorianMonthNameEnglish": "September",
            "gregorianYear": 2020,
            "gregorianDateString": "Sep 05, 2020",
            "dayOfWeek": "Sat",
            "nextPrayer": "lang.asr",
            "nextPrayerRemainingTime": "3:21:59",
            "nextPrayerRemainingTimeHours": 3,
            "nextPrayerRemainingTimeMinutes": 21,
            "nextPrayerRemainingTimeinDateFormat": 1598844060000,
            "currentPrayer": "lang.dhuhar",
            "currentPrayerPassedTime": "1 hour(s) 12 minute(s) ago",
            "currentPrayerPassedTimeHours": 1,
            "currentPrayerPassedTimeMinutes": 12,
            "islamicEvent": null,
            "fajarTime": "04:55 AM",
            "sunriseTime": "06:57 AM",
            "dhuharTime": "01:38 PM",
            "asrTime": "06:11 PM",
            "maghribTime": "08:19 PM",
            "ishaTime": "09:39 PM",
            "qiyamTime": "02:03 AM",
            "isToday": 0,
            "fajarJamahTime": "6:00 AM",
            "zohrJamahTime": "2:00 PM",
            "asarJamahTime": "7:00 PM",
            "magribJamahTime": "8:24 PM",
            "ishaJamahTime": "10:00 PM"
        },
        {
            "responseCode": null,
            "responseDesc": null,
            "fajrHour": 4,
            "fajrMinute": 57,
            "dhuhrHour": 13,
            "dhuhrMinute": 38,
            "asrHour": 18,
            "asrMinute": 9,
            "maghribHour": 20,
            "maghribMinute": 16,
            "ishaHour": 21,
            "ishaMinute": 36,
            "qiyamHour": 2,
            "qiyamMinute": 2,
            "hijriDay": 18,
            "hijriMonth": 1,
            "hijriYear": 1442,
            "hijriDayOfWeek": 0,
            "hiriMonthName": "Muharram",
            "hijriMonthNameEnglish": "Muharram",
            "hijriDate": "18th Muharram, 1442h",
            "sunriseHour": 0,
            "sunriseMinute": 0,
            "gregorianDate": 1599403800000,
            "gregorianDay": 6,
            "gregorianMonth": 8,
            "gregorianMonthName": "September",
            "gregorianMonthNameEnglish": "September",
            "gregorianYear": 2020,
            "gregorianDateString": "Sep 06, 2020",
            "dayOfWeek": "Sun",
            "nextPrayer": "lang.asr",
            "nextPrayerRemainingTime": "3:19:59",
            "nextPrayerRemainingTimeHours": 3,
            "nextPrayerRemainingTimeMinutes": 19,
            "nextPrayerRemainingTimeinDateFormat": 1598843940000,
            "currentPrayer": "lang.dhuhar",
            "currentPrayerPassedTime": "1 hour(s) 12 minute(s) ago",
            "currentPrayerPassedTimeHours": 1,
            "currentPrayerPassedTimeMinutes": 12,
            "islamicEvent": null,
            "fajarTime": "04:57 AM",
            "sunriseTime": "06:59 AM",
            "dhuharTime": "01:38 PM",
            "asrTime": "06:09 PM",
            "maghribTime": "08:16 PM",
            "ishaTime": "09:36 PM",
            "qiyamTime": "02:02 AM",
            "isToday": 0,
            "fajarJamahTime": "6:00 AM",
            "zohrJamahTime": "2:00 PM",
            "asarJamahTime": "7:00 PM",
            "magribJamahTime": "8:21 PM",
            "ishaJamahTime": "10:00 PM"
        },
        {
            "responseCode": null,
            "responseDesc": null,
            "fajrHour": 5,
            "fajrMinute": 0,
            "dhuhrHour": 13,
            "dhuhrMinute": 37,
            "asrHour": 18,
            "asrMinute": 7,
            "maghribHour": 20,
            "maghribMinute": 14,
            "ishaHour": 21,
            "ishaMinute": 34,
            "qiyamHour": 2,
            "qiyamMinute": 4,
            "hijriDay": 19,
            "hijriMonth": 1,
            "hijriYear": 1442,
            "hijriDayOfWeek": 0,
            "hiriMonthName": "Muharram",
            "hijriMonthNameEnglish": "Muharram",
            "hijriDate": "19th Muharram, 1442h",
            "sunriseHour": 0,
            "sunriseMinute": 0,
            "gregorianDate": 1599490200000,
            "gregorianDay": 7,
            "gregorianMonth": 8,
            "gregorianMonthName": "September",
            "gregorianMonthNameEnglish": "September",
            "gregorianYear": 2020,
            "gregorianDateString": "Sep 07, 2020",
            "dayOfWeek": "Mon",
            "nextPrayer": "lang.asr",
            "nextPrayerRemainingTime": "3:17:59",
            "nextPrayerRemainingTimeHours": 3,
            "nextPrayerRemainingTimeMinutes": 17,
            "nextPrayerRemainingTimeinDateFormat": 1598843820000,
            "currentPrayer": "lang.dhuhar",
            "currentPrayerPassedTime": "1 hour(s) 13 minute(s) ago",
            "currentPrayerPassedTimeHours": 1,
            "currentPrayerPassedTimeMinutes": 13,
            "islamicEvent": null,
            "fajarTime": "05:00 AM",
            "sunriseTime": "07:00 AM",
            "dhuharTime": "01:37 PM",
            "asrTime": "06:07 PM",
            "maghribTime": "08:14 PM",
            "ishaTime": "09:34 PM",
            "qiyamTime": "02:04 AM",
            "isToday": 0,
            "fajarJamahTime": "6:00 AM",
            "zohrJamahTime": "2:00 PM",
            "asarJamahTime": "7:00 PM",
            "magribJamahTime": "8:19 PM",
            "ishaJamahTime": "10:00 PM"
        },
        {
            "responseCode": null,
            "responseDesc": null,
            "fajrHour": 5,
            "fajrMinute": 2,
            "dhuhrHour": 13,
            "dhuhrMinute": 37,
            "asrHour": 18,
            "asrMinute": 5,
            "maghribHour": 20,
            "maghribMinute": 12,
            "ishaHour": 21,
            "ishaMinute": 32,
            "qiyamHour": 2,
            "qiyamMinute": 4,
            "hijriDay": 20,
            "hijriMonth": 1,
            "hijriYear": 1442,
            "hijriDayOfWeek": 0,
            "hiriMonthName": "Muharram",
            "hijriMonthNameEnglish": "Muharram",
            "hijriDate": "20th Muharram, 1442h",
            "sunriseHour": 0,
            "sunriseMinute": 0,
            "gregorianDate": 1599576600000,
            "gregorianDay": 8,
            "gregorianMonth": 8,
            "gregorianMonthName": "September",
            "gregorianMonthNameEnglish": "September",
            "gregorianYear": 2020,
            "gregorianDateString": "Sep 08, 2020",
            "dayOfWeek": "Tue",
            "nextPrayer": "lang.asr",
            "nextPrayerRemainingTime": "3:15:59",
            "nextPrayerRemainingTimeHours": 3,
            "nextPrayerRemainingTimeMinutes": 15,
            "nextPrayerRemainingTimeinDateFormat": 1598843700000,
            "currentPrayer": "lang.dhuhar",
            "currentPrayerPassedTime": "1 hour(s) 13 minute(s) ago",
            "currentPrayerPassedTimeHours": 1,
            "currentPrayerPassedTimeMinutes": 13,
            "islamicEvent": null,
            "fajarTime": "05:02 AM",
            "sunriseTime": "07:02 AM",
            "dhuharTime": "01:37 PM",
            "asrTime": "06:05 PM",
            "maghribTime": "08:12 PM",
            "ishaTime": "09:32 PM",
            "qiyamTime": "02:04 AM",
            "isToday": 0,
            "fajarJamahTime": "6:00 AM",
            "zohrJamahTime": "2:00 PM",
            "asarJamahTime": "7:00 PM",
            "magribJamahTime": "8:17 PM",
            "ishaJamahTime": "10:00 PM"
        },
        {
            "responseCode": null,
            "responseDesc": null,
            "fajrHour": 5,
            "fajrMinute": 4,
            "dhuhrHour": 13,
            "dhuhrMinute": 37,
            "asrHour": 18,
            "asrMinute": 3,
            "maghribHour": 20,
            "maghribMinute": 9,
            "ishaHour": 21,
            "ishaMinute": 29,
            "qiyamHour": 2,
            "qiyamMinute": 5,
            "hijriDay": 21,
            "hijriMonth": 1,
            "hijriYear": 1442,
            "hijriDayOfWeek": 0,
            "hiriMonthName": "Muharram",
            "hijriMonthNameEnglish": "Muharram",
            "hijriDate": "21st Muharram, 1442h",
            "sunriseHour": 0,
            "sunriseMinute": 0,
            "gregorianDate": 1599663000000,
            "gregorianDay": 9,
            "gregorianMonth": 8,
            "gregorianMonthName": "September",
            "gregorianMonthNameEnglish": "September",
            "gregorianYear": 2020,
            "gregorianDateString": "Sep 09, 2020",
            "dayOfWeek": "Wed",
            "nextPrayer": "lang.asr",
            "nextPrayerRemainingTime": "3:13:59",
            "nextPrayerRemainingTimeHours": 3,
            "nextPrayerRemainingTimeMinutes": 13,
            "nextPrayerRemainingTimeinDateFormat": 1598843580000,
            "currentPrayer": "lang.dhuhar",
            "currentPrayerPassedTime": "1 hour(s) 13 minute(s) ago",
            "currentPrayerPassedTimeHours": 1,
            "currentPrayerPassedTimeMinutes": 13,
            "islamicEvent": null,
            "fajarTime": "05:04 AM",
            "sunriseTime": "07:04 AM",
            "dhuharTime": "01:37 PM",
            "asrTime": "06:03 PM",
            "maghribTime": "08:09 PM",
            "ishaTime": "09:29 PM",
            "qiyamTime": "02:05 AM",
            "isToday": 0,
            "fajarJamahTime": "6:00 AM",
            "zohrJamahTime": "2:00 PM",
            "asarJamahTime": "7:00 PM",
            "magribJamahTime": "8:14 PM",
            "ishaJamahTime": "10:00 PM"
        },
        {
            "responseCode": null,
            "responseDesc": null,
            "fajrHour": 5,
            "fajrMinute": 7,
            "dhuhrHour": 13,
            "dhuhrMinute": 36,
            "asrHour": 18,
            "asrMinute": 1,
            "maghribHour": 20,
            "maghribMinute": 7,
            "ishaHour": 21,
            "ishaMinute": 27,
            "qiyamHour": 2,
            "qiyamMinute": 7,
            "hijriDay": 22,
            "hijriMonth": 1,
            "hijriYear": 1442,
            "hijriDayOfWeek": 0,
            "hiriMonthName": "Muharram",
            "hijriMonthNameEnglish": "Muharram",
            "hijriDate": "22nd Muharram, 1442h",
            "sunriseHour": 0,
            "sunriseMinute": 0,
            "gregorianDate": 1599749400000,
            "gregorianDay": 10,
            "gregorianMonth": 8,
            "gregorianMonthName": "September",
            "gregorianMonthNameEnglish": "September",
            "gregorianYear": 2020,
            "gregorianDateString": "Sep 10, 2020",
            "dayOfWeek": "Thu",
            "nextPrayer": "lang.asr",
            "nextPrayerRemainingTime": "3:11:59",
            "nextPrayerRemainingTimeHours": 3,
            "nextPrayerRemainingTimeMinutes": 11,
            "nextPrayerRemainingTimeinDateFormat": 1598843460000,
            "currentPrayer": "lang.dhuhar",
            "currentPrayerPassedTime": "1 hour(s) 14 minute(s) ago",
            "currentPrayerPassedTimeHours": 1,
            "currentPrayerPassedTimeMinutes": 14,
            "islamicEvent": null,
            "fajarTime": "05:07 AM",
            "sunriseTime": "07:05 AM",
            "dhuharTime": "01:36 PM",
            "asrTime": "06:01 PM",
            "maghribTime": "08:07 PM",
            "ishaTime": "09:27 PM",
            "qiyamTime": "02:07 AM",
            "isToday": 0,
            "fajarJamahTime": "6:00 AM",
            "zohrJamahTime": "2:00 PM",
            "asarJamahTime": "7:00 PM",
            "magribJamahTime": "8:12 PM",
            "ishaJamahTime": "10:00 PM"
        },
        {
            "responseCode": null,
            "responseDesc": null,
            "fajrHour": 5,
            "fajrMinute": 9,
            "dhuhrHour": 13,
            "dhuhrMinute": 36,
            "asrHour": 18,
            "asrMinute": 0,
            "maghribHour": 20,
            "maghribMinute": 5,
            "ishaHour": 21,
            "ishaMinute": 25,
            "qiyamHour": 2,
            "qiyamMinute": 7,
            "hijriDay": 23,
            "hijriMonth": 1,
            "hijriYear": 1442,
            "hijriDayOfWeek": 0,
            "hiriMonthName": "Muharram",
            "hijriMonthNameEnglish": "Muharram",
            "hijriDate": "23rd Muharram, 1442h",
            "sunriseHour": 0,
            "sunriseMinute": 0,
            "gregorianDate": 1599835800000,
            "gregorianDay": 11,
            "gregorianMonth": 8,
            "gregorianMonthName": "September",
            "gregorianMonthNameEnglish": "September",
            "gregorianYear": 2020,
            "gregorianDateString": "Sep 11, 2020",
            "dayOfWeek": "Fri",
            "nextPrayer": "lang.asr",
            "nextPrayerRemainingTime": "3:10:59",
            "nextPrayerRemainingTimeHours": 3,
            "nextPrayerRemainingTimeMinutes": 10,
            "nextPrayerRemainingTimeinDateFormat": 1598843400000,
            "currentPrayer": "lang.dhuhar",
            "currentPrayerPassedTime": "1 hour(s) 14 minute(s) ago",
            "currentPrayerPassedTimeHours": 1,
            "currentPrayerPassedTimeMinutes": 14,
            "islamicEvent": null,
            "fajarTime": "05:09 AM",
            "sunriseTime": "07:07 AM",
            "dhuharTime": "01:36 PM",
            "asrTime": "06:00 PM",
            "maghribTime": "08:05 PM",
            "ishaTime": "09:25 PM",
            "qiyamTime": "02:07 AM",
            "isToday": 0,
            "fajarJamahTime": "6:15 AM",
            "zohrJamahTime": "2:00 PM",
            "asarJamahTime": "6:30 PM",
            "magribJamahTime": "8:10 PM",
            "ishaJamahTime": "9:45 PM"
        },
        {
            "responseCode": null,
            "responseDesc": null,
            "fajrHour": 5,
            "fajrMinute": 11,
            "dhuhrHour": 13,
            "dhuhrMinute": 35,
            "asrHour": 17,
            "asrMinute": 58,
            "maghribHour": 20,
            "maghribMinute": 2,
            "ishaHour": 21,
            "ishaMinute": 22,
            "qiyamHour": 2,
            "qiyamMinute": 8,
            "hijriDay": 24,
            "hijriMonth": 1,
            "hijriYear": 1442,
            "hijriDayOfWeek": 0,
            "hiriMonthName": "Muharram",
            "hijriMonthNameEnglish": "Muharram",
            "hijriDate": "24th Muharram, 1442h",
            "sunriseHour": 0,
            "sunriseMinute": 0,
            "gregorianDate": 1599922200000,
            "gregorianDay": 12,
            "gregorianMonth": 8,
            "gregorianMonthName": "September",
            "gregorianMonthNameEnglish": "September",
            "gregorianYear": 2020,
            "gregorianDateString": "Sep 12, 2020",
            "dayOfWeek": "Sat",
            "nextPrayer": "lang.asr",
            "nextPrayerRemainingTime": "3:8:59",
            "nextPrayerRemainingTimeHours": 3,
            "nextPrayerRemainingTimeMinutes": 8,
            "nextPrayerRemainingTimeinDateFormat": 1598843280000,
            "currentPrayer": "lang.dhuhar",
            "currentPrayerPassedTime": "1 hour(s) 15 minute(s) ago",
            "currentPrayerPassedTimeHours": 1,
            "currentPrayerPassedTimeMinutes": 15,
            "islamicEvent": null,
            "fajarTime": "05:11 AM",
            "sunriseTime": "07:08 AM",
            "dhuharTime": "01:35 PM",
            "asrTime": "05:58 PM",
            "maghribTime": "08:02 PM",
            "ishaTime": "09:22 PM",
            "qiyamTime": "02:08 AM",
            "isToday": 0,
            "fajarJamahTime": "6:15 AM",
            "zohrJamahTime": "2:00 PM",
            "asarJamahTime": "6:30 PM",
            "magribJamahTime": "8:07 PM",
            "ishaJamahTime": "9:45 PM"
        },
        {
            "responseCode": null,
            "responseDesc": null,
            "fajrHour": 5,
            "fajrMinute": 13,
            "dhuhrHour": 13,
            "dhuhrMinute": 35,
            "asrHour": 17,
            "asrMinute": 56,
            "maghribHour": 20,
            "maghribMinute": 0,
            "ishaHour": 21,
            "ishaMinute": 20,
            "qiyamHour": 2,
            "qiyamMinute": 8,
            "hijriDay": 25,
            "hijriMonth": 1,
            "hijriYear": 1442,
            "hijriDayOfWeek": 0,
            "hiriMonthName": "Muharram",
            "hijriMonthNameEnglish": "Muharram",
            "hijriDate": "25th Muharram, 1442h",
            "sunriseHour": 0,
            "sunriseMinute": 0,
            "gregorianDate": 1600008600000,
            "gregorianDay": 13,
            "gregorianMonth": 8,
            "gregorianMonthName": "September",
            "gregorianMonthNameEnglish": "September",
            "gregorianYear": 2020,
            "gregorianDateString": "Sep 13, 2020",
            "dayOfWeek": "Sun",
            "nextPrayer": "lang.asr",
            "nextPrayerRemainingTime": "3:6:59",
            "nextPrayerRemainingTimeHours": 3,
            "nextPrayerRemainingTimeMinutes": 6,
            "nextPrayerRemainingTimeinDateFormat": 1598843160000,
            "currentPrayer": "lang.dhuhar",
            "currentPrayerPassedTime": "1 hour(s) 15 minute(s) ago",
            "currentPrayerPassedTimeHours": 1,
            "currentPrayerPassedTimeMinutes": 15,
            "islamicEvent": null,
            "fajarTime": "05:13 AM",
            "sunriseTime": "07:10 AM",
            "dhuharTime": "01:35 PM",
            "asrTime": "05:56 PM",
            "maghribTime": "08:00 PM",
            "ishaTime": "09:20 PM",
            "qiyamTime": "02:08 AM",
            "isToday": 0,
            "fajarJamahTime": "6:15 AM",
            "zohrJamahTime": "2:00 PM",
            "asarJamahTime": "6:30 PM",
            "magribJamahTime": "8:05 PM",
            "ishaJamahTime": "9:45 PM"
        },
        {
            "responseCode": null,
            "responseDesc": null,
            "fajrHour": 5,
            "fajrMinute": 15,
            "dhuhrHour": 13,
            "dhuhrMinute": 35,
            "asrHour": 17,
            "asrMinute": 54,
            "maghribHour": 19,
            "maghribMinute": 58,
            "ishaHour": 21,
            "ishaMinute": 18,
            "qiyamHour": 2,
            "qiyamMinute": 8,
            "hijriDay": 26,
            "hijriMonth": 1,
            "hijriYear": 1442,
            "hijriDayOfWeek": 0,
            "hiriMonthName": "Muharram",
            "hijriMonthNameEnglish": "Muharram",
            "hijriDate": "26th Muharram, 1442h",
            "sunriseHour": 0,
            "sunriseMinute": 0,
            "gregorianDate": 1600095000000,
            "gregorianDay": 14,
            "gregorianMonth": 8,
            "gregorianMonthName": "September",
            "gregorianMonthNameEnglish": "September",
            "gregorianYear": 2020,
            "gregorianDateString": "Sep 14, 2020",
            "dayOfWeek": "Mon",
            "nextPrayer": "lang.asr",
            "nextPrayerRemainingTime": "3:4:59",
            "nextPrayerRemainingTimeHours": 3,
            "nextPrayerRemainingTimeMinutes": 4,
            "nextPrayerRemainingTimeinDateFormat": 1598843040000,
            "currentPrayer": "lang.dhuhar",
            "currentPrayerPassedTime": "1 hour(s) 15 minute(s) ago",
            "currentPrayerPassedTimeHours": 1,
            "currentPrayerPassedTimeMinutes": 15,
            "islamicEvent": null,
            "fajarTime": "05:15 AM",
            "sunriseTime": "07:12 AM",
            "dhuharTime": "01:35 PM",
            "asrTime": "05:54 PM",
            "maghribTime": "07:58 PM",
            "ishaTime": "09:18 PM",
            "qiyamTime": "02:08 AM",
            "isToday": 0,
            "fajarJamahTime": "6:15 AM",
            "zohrJamahTime": "2:00 PM",
            "asarJamahTime": "6:30 PM",
            "magribJamahTime": "8:03 PM",
            "ishaJamahTime": "9:45 PM"
        },
        {
            "responseCode": null,
            "responseDesc": null,
            "fajrHour": 5,
            "fajrMinute": 17,
            "dhuhrHour": 13,
            "dhuhrMinute": 34,
            "asrHour": 17,
            "asrMinute": 52,
            "maghribHour": 19,
            "maghribMinute": 55,
            "ishaHour": 21,
            "ishaMinute": 15,
            "qiyamHour": 2,
            "qiyamMinute": 9,
            "hijriDay": 27,
            "hijriMonth": 1,
            "hijriYear": 1442,
            "hijriDayOfWeek": 0,
            "hiriMonthName": "Muharram",
            "hijriMonthNameEnglish": "Muharram",
            "hijriDate": "27th Muharram, 1442h",
            "sunriseHour": 0,
            "sunriseMinute": 0,
            "gregorianDate": 1600181400000,
            "gregorianDay": 15,
            "gregorianMonth": 8,
            "gregorianMonthName": "September",
            "gregorianMonthNameEnglish": "September",
            "gregorianYear": 2020,
            "gregorianDateString": "Sep 15, 2020",
            "dayOfWeek": "Tue",
            "nextPrayer": "lang.asr",
            "nextPrayerRemainingTime": "3:2:59",
            "nextPrayerRemainingTimeHours": 3,
            "nextPrayerRemainingTimeMinutes": 2,
            "nextPrayerRemainingTimeinDateFormat": 1598842920000,
            "currentPrayer": "lang.dhuhar",
            "currentPrayerPassedTime": "1 hour(s) 16 minute(s) ago",
            "currentPrayerPassedTimeHours": 1,
            "currentPrayerPassedTimeMinutes": 16,
            "islamicEvent": null,
            "fajarTime": "05:17 AM",
            "sunriseTime": "07:13 AM",
            "dhuharTime": "01:34 PM",
            "asrTime": "05:52 PM",
            "maghribTime": "07:55 PM",
            "ishaTime": "09:15 PM",
            "qiyamTime": "02:09 AM",
            "isToday": 0,
            "fajarJamahTime": "6:15 AM",
            "zohrJamahTime": "2:00 PM",
            "asarJamahTime": "6:30 PM",
            "magribJamahTime": "8:00 PM",
            "ishaJamahTime": "9:45 PM"
        },
        {
            "responseCode": null,
            "responseDesc": null,
            "fajrHour": 5,
            "fajrMinute": 19,
            "dhuhrHour": 13,
            "dhuhrMinute": 34,
            "asrHour": 17,
            "asrMinute": 50,
            "maghribHour": 19,
            "maghribMinute": 53,
            "ishaHour": 21,
            "ishaMinute": 13,
            "qiyamHour": 2,
            "qiyamMinute": 9,
            "hijriDay": 28,
            "hijriMonth": 1,
            "hijriYear": 1442,
            "hijriDayOfWeek": 0,
            "hiriMonthName": "Muharram",
            "hijriMonthNameEnglish": "Muharram",
            "hijriDate": "28th Muharram, 1442h",
            "sunriseHour": 0,
            "sunriseMinute": 0,
            "gregorianDate": 1600267800000,
            "gregorianDay": 16,
            "gregorianMonth": 8,
            "gregorianMonthName": "September",
            "gregorianMonthNameEnglish": "September",
            "gregorianYear": 2020,
            "gregorianDateString": "Sep 16, 2020",
            "dayOfWeek": "Wed",
            "nextPrayer": "lang.asr",
            "nextPrayerRemainingTime": "3:0:59",
            "nextPrayerRemainingTimeHours": 3,
            "nextPrayerRemainingTimeMinutes": 0,
            "nextPrayerRemainingTimeinDateFormat": 1598842800000,
            "currentPrayer": "lang.dhuhar",
            "currentPrayerPassedTime": "1 hour(s) 16 minute(s) ago",
            "currentPrayerPassedTimeHours": 1,
            "currentPrayerPassedTimeMinutes": 16,
            "islamicEvent": null,
            "fajarTime": "05:19 AM",
            "sunriseTime": "07:15 AM",
            "dhuharTime": "01:34 PM",
            "asrTime": "05:50 PM",
            "maghribTime": "07:53 PM",
            "ishaTime": "09:13 PM",
            "qiyamTime": "02:09 AM",
            "isToday": 0,
            "fajarJamahTime": "6:15 AM",
            "zohrJamahTime": "2:00 PM",
            "asarJamahTime": "6:30 PM",
            "magribJamahTime": "7:58 PM",
            "ishaJamahTime": "9:45 PM"
        },
        {
            "responseCode": null,
            "responseDesc": null,
            "fajrHour": 5,
            "fajrMinute": 21,
            "dhuhrHour": 13,
            "dhuhrMinute": 34,
            "asrHour": 17,
            "asrMinute": 48,
            "maghribHour": 19,
            "maghribMinute": 51,
            "ishaHour": 21,
            "ishaMinute": 11,
            "qiyamHour": 2,
            "qiyamMinute": 11,
            "hijriDay": 29,
            "hijriMonth": 1,
            "hijriYear": 1442,
            "hijriDayOfWeek": 0,
            "hiriMonthName": "Muharram",
            "hijriMonthNameEnglish": "Muharram",
            "hijriDate": "29th Muharram, 1442h",
            "sunriseHour": 0,
            "sunriseMinute": 0,
            "gregorianDate": 1600354200000,
            "gregorianDay": 17,
            "gregorianMonth": 8,
            "gregorianMonthName": "September",
            "gregorianMonthNameEnglish": "September",
            "gregorianYear": 2020,
            "gregorianDateString": "Sep 17, 2020",
            "dayOfWeek": "Thu",
            "nextPrayer": "lang.asr",
            "nextPrayerRemainingTime": "2:58:59",
            "nextPrayerRemainingTimeHours": 2,
            "nextPrayerRemainingTimeMinutes": 58,
            "nextPrayerRemainingTimeinDateFormat": 1598842680000,
            "currentPrayer": "lang.dhuhar",
            "currentPrayerPassedTime": "1 hour(s) 16 minute(s) ago",
            "currentPrayerPassedTimeHours": 1,
            "currentPrayerPassedTimeMinutes": 16,
            "islamicEvent": null,
            "fajarTime": "05:21 AM",
            "sunriseTime": "07:17 AM",
            "dhuharTime": "01:34 PM",
            "asrTime": "05:48 PM",
            "maghribTime": "07:51 PM",
            "ishaTime": "09:11 PM",
            "qiyamTime": "02:11 AM",
            "isToday": 0,
            "fajarJamahTime": "6:15 AM",
            "zohrJamahTime": "2:00 PM",
            "asarJamahTime": "6:30 PM",
            "magribJamahTime": "7:56 PM",
            "ishaJamahTime": "9:45 PM"
        },
        {
            "responseCode": null,
            "responseDesc": null,
            "fajrHour": 5,
            "fajrMinute": 24,
            "dhuhrHour": 13,
            "dhuhrMinute": 33,
            "asrHour": 17,
            "asrMinute": 46,
            "maghribHour": 19,
            "maghribMinute": 48,
            "ishaHour": 21,
            "ishaMinute": 8,
            "qiyamHour": 2,
            "qiyamMinute": 12,
            "hijriDay": 1,
            "hijriMonth": 2,
            "hijriYear": 1442,
            "hijriDayOfWeek": 0,
            "hiriMonthName": "Safar",
            "hijriMonthNameEnglish": "Safar",
            "hijriDate": "1st Safar, 1442h",
            "sunriseHour": 0,
            "sunriseMinute": 0,
            "gregorianDate": 1600440600000,
            "gregorianDay": 18,
            "gregorianMonth": 8,
            "gregorianMonthName": "September",
            "gregorianMonthNameEnglish": "September",
            "gregorianYear": 2020,
            "gregorianDateString": "Sep 18, 2020",
            "dayOfWeek": "Fri",
            "nextPrayer": "lang.asr",
            "nextPrayerRemainingTime": "2:56:59",
            "nextPrayerRemainingTimeHours": 2,
            "nextPrayerRemainingTimeMinutes": 56,
            "nextPrayerRemainingTimeinDateFormat": 1598842560000,
            "currentPrayer": "lang.dhuhar",
            "currentPrayerPassedTime": "1 hour(s) 17 minute(s) ago",
            "currentPrayerPassedTimeHours": 1,
            "currentPrayerPassedTimeMinutes": 17,
            "islamicEvent": null,
            "fajarTime": "05:24 AM",
            "sunriseTime": "07:18 AM",
            "dhuharTime": "01:33 PM",
            "asrTime": "05:46 PM",
            "maghribTime": "07:48 PM",
            "ishaTime": "09:08 PM",
            "qiyamTime": "02:12 AM",
            "isToday": 0,
            "fajarJamahTime": "6:30 AM",
            "zohrJamahTime": "2:00 PM",
            "asarJamahTime": "6:15 PM",
            "magribJamahTime": "7:53 PM",
            "ishaJamahTime": "9:30 PM"
        },
        {
            "responseCode": null,
            "responseDesc": null,
            "fajrHour": 5,
            "fajrMinute": 26,
            "dhuhrHour": 13,
            "dhuhrMinute": 33,
            "asrHour": 17,
            "asrMinute": 44,
            "maghribHour": 19,
            "maghribMinute": 46,
            "ishaHour": 21,
            "ishaMinute": 6,
            "qiyamHour": 2,
            "qiyamMinute": 12,
            "hijriDay": 2,
            "hijriMonth": 2,
            "hijriYear": 1442,
            "hijriDayOfWeek": 0,
            "hiriMonthName": "Safar",
            "hijriMonthNameEnglish": "Safar",
            "hijriDate": "2nd Safar, 1442h",
            "sunriseHour": 0,
            "sunriseMinute": 0,
            "gregorianDate": 1600527000000,
            "gregorianDay": 19,
            "gregorianMonth": 8,
            "gregorianMonthName": "September",
            "gregorianMonthNameEnglish": "September",
            "gregorianYear": 2020,
            "gregorianDateString": "Sep 19, 2020",
            "dayOfWeek": "Sat",
            "nextPrayer": "lang.asr",
            "nextPrayerRemainingTime": "2:54:59",
            "nextPrayerRemainingTimeHours": 2,
            "nextPrayerRemainingTimeMinutes": 54,
            "nextPrayerRemainingTimeinDateFormat": 1598842440000,
            "currentPrayer": "lang.dhuhar",
            "currentPrayerPassedTime": "1 hour(s) 17 minute(s) ago",
            "currentPrayerPassedTimeHours": 1,
            "currentPrayerPassedTimeMinutes": 17,
            "islamicEvent": null,
            "fajarTime": "05:26 AM",
            "sunriseTime": "07:20 AM",
            "dhuharTime": "01:33 PM",
            "asrTime": "05:44 PM",
            "maghribTime": "07:46 PM",
            "ishaTime": "09:06 PM",
            "qiyamTime": "02:12 AM",
            "isToday": 0,
            "fajarJamahTime": "6:30 AM",
            "zohrJamahTime": "2:00 PM",
            "asarJamahTime": "6:15 PM",
            "magribJamahTime": "7:51 PM",
            "ishaJamahTime": "9:30 PM"
        },
        {
            "responseCode": null,
            "responseDesc": null,
            "fajrHour": 5,
            "fajrMinute": 28,
            "dhuhrHour": 13,
            "dhuhrMinute": 33,
            "asrHour": 17,
            "asrMinute": 42,
            "maghribHour": 19,
            "maghribMinute": 44,
            "ishaHour": 21,
            "ishaMinute": 4,
            "qiyamHour": 2,
            "qiyamMinute": 12,
            "hijriDay": 3,
            "hijriMonth": 2,
            "hijriYear": 1442,
            "hijriDayOfWeek": 0,
            "hiriMonthName": "Safar",
            "hijriMonthNameEnglish": "Safar",
            "hijriDate": "3rd Safar, 1442h",
            "sunriseHour": 0,
            "sunriseMinute": 0,
            "gregorianDate": 1600613400000,
            "gregorianDay": 20,
            "gregorianMonth": 8,
            "gregorianMonthName": "September",
            "gregorianMonthNameEnglish": "September",
            "gregorianYear": 2020,
            "gregorianDateString": "Sep 20, 2020",
            "dayOfWeek": "Sun",
            "nextPrayer": "lang.asr",
            "nextPrayerRemainingTime": "2:52:59",
            "nextPrayerRemainingTimeHours": 2,
            "nextPrayerRemainingTimeMinutes": 52,
            "nextPrayerRemainingTimeinDateFormat": 1598842320000,
            "currentPrayer": "lang.dhuhar",
            "currentPrayerPassedTime": "1 hour(s) 17 minute(s) ago",
            "currentPrayerPassedTimeHours": 1,
            "currentPrayerPassedTimeMinutes": 17,
            "islamicEvent": null,
            "fajarTime": "05:28 AM",
            "sunriseTime": "07:22 AM",
            "dhuharTime": "01:33 PM",
            "asrTime": "05:42 PM",
            "maghribTime": "07:44 PM",
            "ishaTime": "09:04 PM",
            "qiyamTime": "02:12 AM",
            "isToday": 0,
            "fajarJamahTime": "6:30 AM",
            "zohrJamahTime": "2:00 PM",
            "asarJamahTime": "6:15 PM",
            "magribJamahTime": "7:49 PM",
            "ishaJamahTime": "9:30 PM"
        },
        {
            "responseCode": null,
            "responseDesc": null,
            "fajrHour": 5,
            "fajrMinute": 30,
            "dhuhrHour": 13,
            "dhuhrMinute": 32,
            "asrHour": 17,
            "asrMinute": 40,
            "maghribHour": 19,
            "maghribMinute": 41,
            "ishaHour": 21,
            "ishaMinute": 1,
            "qiyamHour": 2,
            "qiyamMinute": 13,
            "hijriDay": 4,
            "hijriMonth": 2,
            "hijriYear": 1442,
            "hijriDayOfWeek": 0,
            "hiriMonthName": "Safar",
            "hijriMonthNameEnglish": "Safar",
            "hijriDate": "4th Safar, 1442h",
            "sunriseHour": 0,
            "sunriseMinute": 0,
            "gregorianDate": 1600699800000,
            "gregorianDay": 21,
            "gregorianMonth": 8,
            "gregorianMonthName": "September",
            "gregorianMonthNameEnglish": "September",
            "gregorianYear": 2020,
            "gregorianDateString": "Sep 21, 2020",
            "dayOfWeek": "Mon",
            "nextPrayer": "lang.asr",
            "nextPrayerRemainingTime": "2:50:59",
            "nextPrayerRemainingTimeHours": 2,
            "nextPrayerRemainingTimeMinutes": 50,
            "nextPrayerRemainingTimeinDateFormat": 1598842200000,
            "currentPrayer": "lang.dhuhar",
            "currentPrayerPassedTime": "1 hour(s) 18 minute(s) ago",
            "currentPrayerPassedTimeHours": 1,
            "currentPrayerPassedTimeMinutes": 18,
            "islamicEvent": null,
            "fajarTime": "05:30 AM",
            "sunriseTime": "07:23 AM",
            "dhuharTime": "01:32 PM",
            "asrTime": "05:40 PM",
            "maghribTime": "07:41 PM",
            "ishaTime": "09:01 PM",
            "qiyamTime": "02:13 AM",
            "isToday": 0,
            "fajarJamahTime": "6:30 AM",
            "zohrJamahTime": "2:00 PM",
            "asarJamahTime": "6:15 PM",
            "magribJamahTime": "7:46 PM",
            "ishaJamahTime": "9:30 PM"
        },
        {
            "responseCode": null,
            "responseDesc": null,
            "fajrHour": 5,
            "fajrMinute": 32,
            "dhuhrHour": 13,
            "dhuhrMinute": 32,
            "asrHour": 17,
            "asrMinute": 38,
            "maghribHour": 19,
            "maghribMinute": 39,
            "ishaHour": 20,
            "ishaMinute": 59,
            "qiyamHour": 2,
            "qiyamMinute": 13,
            "hijriDay": 5,
            "hijriMonth": 2,
            "hijriYear": 1442,
            "hijriDayOfWeek": 0,
            "hiriMonthName": "Safar",
            "hijriMonthNameEnglish": "Safar",
            "hijriDate": "5th Safar, 1442h",
            "sunriseHour": 0,
            "sunriseMinute": 0,
            "gregorianDate": 1600786200000,
            "gregorianDay": 22,
            "gregorianMonth": 8,
            "gregorianMonthName": "September",
            "gregorianMonthNameEnglish": "September",
            "gregorianYear": 2020,
            "gregorianDateString": "Sep 22, 2020",
            "dayOfWeek": "Tue",
            "nextPrayer": "lang.asr",
            "nextPrayerRemainingTime": "2:48:59",
            "nextPrayerRemainingTimeHours": 2,
            "nextPrayerRemainingTimeMinutes": 48,
            "nextPrayerRemainingTimeinDateFormat": 1598842080000,
            "currentPrayer": "lang.dhuhar",
            "currentPrayerPassedTime": "1 hour(s) 18 minute(s) ago",
            "currentPrayerPassedTimeHours": 1,
            "currentPrayerPassedTimeMinutes": 18,
            "islamicEvent": null,
            "fajarTime": "05:32 AM",
            "sunriseTime": "07:25 AM",
            "dhuharTime": "01:32 PM",
            "asrTime": "05:38 PM",
            "maghribTime": "07:39 PM",
            "ishaTime": "08:59 PM",
            "qiyamTime": "02:13 AM",
            "isToday": 0,
            "fajarJamahTime": "6:30 AM",
            "zohrJamahTime": "2:00 PM",
            "asarJamahTime": "6:15 PM",
            "magribJamahTime": "7:44 PM",
            "ishaJamahTime": "9:30 PM"
        },
        {
            "responseCode": null,
            "responseDesc": null,
            "fajrHour": 5,
            "fajrMinute": 34,
            "dhuhrHour": 13,
            "dhuhrMinute": 32,
            "asrHour": 17,
            "asrMinute": 36,
            "maghribHour": 19,
            "maghribMinute": 36,
            "ishaHour": 20,
            "ishaMinute": 56,
            "qiyamHour": 2,
            "qiyamMinute": 14,
            "hijriDay": 6,
            "hijriMonth": 2,
            "hijriYear": 1442,
            "hijriDayOfWeek": 0,
            "hiriMonthName": "Safar",
            "hijriMonthNameEnglish": "Safar",
            "hijriDate": "6th Safar, 1442h",
            "sunriseHour": 0,
            "sunriseMinute": 0,
            "gregorianDate": 1600872600000,
            "gregorianDay": 23,
            "gregorianMonth": 8,
            "gregorianMonthName": "September",
            "gregorianMonthNameEnglish": "September",
            "gregorianYear": 2020,
            "gregorianDateString": "Sep 23, 2020",
            "dayOfWeek": "Wed",
            "nextPrayer": "lang.asr",
            "nextPrayerRemainingTime": "2:46:59",
            "nextPrayerRemainingTimeHours": 2,
            "nextPrayerRemainingTimeMinutes": 46,
            "nextPrayerRemainingTimeinDateFormat": 1598841960000,
            "currentPrayer": "lang.dhuhar",
            "currentPrayerPassedTime": "1 hour(s) 18 minute(s) ago",
            "currentPrayerPassedTimeHours": 1,
            "currentPrayerPassedTimeMinutes": 18,
            "islamicEvent": null,
            "fajarTime": "05:34 AM",
            "sunriseTime": "07:27 AM",
            "dhuharTime": "01:32 PM",
            "asrTime": "05:36 PM",
            "maghribTime": "07:36 PM",
            "ishaTime": "08:56 PM",
            "qiyamTime": "02:14 AM",
            "isToday": 0,
            "fajarJamahTime": "6:30 AM",
            "zohrJamahTime": "2:00 PM",
            "asarJamahTime": "6:15 PM",
            "magribJamahTime": "7:41 PM",
            "ishaJamahTime": "9:30 PM"
        },
        {
            "responseCode": null,
            "responseDesc": null,
            "fajrHour": 5,
            "fajrMinute": 35,
            "dhuhrHour": 13,
            "dhuhrMinute": 31,
            "asrHour": 17,
            "asrMinute": 34,
            "maghribHour": 19,
            "maghribMinute": 34,
            "ishaHour": 20,
            "ishaMinute": 54,
            "qiyamHour": 2,
            "qiyamMinute": 14,
            "hijriDay": 7,
            "hijriMonth": 2,
            "hijriYear": 1442,
            "hijriDayOfWeek": 0,
            "hiriMonthName": "Safar",
            "hijriMonthNameEnglish": "Safar",
            "hijriDate": "7th Safar, 1442h",
            "sunriseHour": 0,
            "sunriseMinute": 0,
            "gregorianDate": 1600959000000,
            "gregorianDay": 24,
            "gregorianMonth": 8,
            "gregorianMonthName": "September",
            "gregorianMonthNameEnglish": "September",
            "gregorianYear": 2020,
            "gregorianDateString": "Sep 24, 2020",
            "dayOfWeek": "Thu",
            "nextPrayer": "lang.asr",
            "nextPrayerRemainingTime": "2:44:59",
            "nextPrayerRemainingTimeHours": 2,
            "nextPrayerRemainingTimeMinutes": 44,
            "nextPrayerRemainingTimeinDateFormat": 1598841840000,
            "currentPrayer": "lang.dhuhar",
            "currentPrayerPassedTime": "1 hour(s) 19 minute(s) ago",
            "currentPrayerPassedTimeHours": 1,
            "currentPrayerPassedTimeMinutes": 19,
            "islamicEvent": null,
            "fajarTime": "05:35 AM",
            "sunriseTime": "07:28 AM",
            "dhuharTime": "01:31 PM",
            "asrTime": "05:34 PM",
            "maghribTime": "07:34 PM",
            "ishaTime": "08:54 PM",
            "qiyamTime": "02:14 AM",
            "isToday": 0,
            "fajarJamahTime": "6:30 AM",
            "zohrJamahTime": "2:00 PM",
            "asarJamahTime": "6:15 PM",
            "magribJamahTime": "7:39 PM",
            "ishaJamahTime": "9:30 PM"
        },
        {
            "responseCode": null,
            "responseDesc": null,
            "fajrHour": 5,
            "fajrMinute": 37,
            "dhuhrHour": 13,
            "dhuhrMinute": 31,
            "asrHour": 17,
            "asrMinute": 32,
            "maghribHour": 19,
            "maghribMinute": 32,
            "ishaHour": 20,
            "ishaMinute": 52,
            "qiyamHour": 2,
            "qiyamMinute": 14,
            "hijriDay": 8,
            "hijriMonth": 2,
            "hijriYear": 1442,
            "hijriDayOfWeek": 0,
            "hiriMonthName": "Safar",
            "hijriMonthNameEnglish": "Safar",
            "hijriDate": "8th Safar, 1442h",
            "sunriseHour": 0,
            "sunriseMinute": 0,
            "gregorianDate": 1601045400000,
            "gregorianDay": 25,
            "gregorianMonth": 8,
            "gregorianMonthName": "September",
            "gregorianMonthNameEnglish": "September",
            "gregorianYear": 2020,
            "gregorianDateString": "Sep 25, 2020",
            "dayOfWeek": "Fri",
            "nextPrayer": "lang.asr",
            "nextPrayerRemainingTime": "2:42:59",
            "nextPrayerRemainingTimeHours": 2,
            "nextPrayerRemainingTimeMinutes": 42,
            "nextPrayerRemainingTimeinDateFormat": 1598841720000,
            "currentPrayer": "lang.dhuhar",
            "currentPrayerPassedTime": "1 hour(s) 19 minute(s) ago",
            "currentPrayerPassedTimeHours": 1,
            "currentPrayerPassedTimeMinutes": 19,
            "islamicEvent": null,
            "fajarTime": "05:37 AM",
            "sunriseTime": "07:30 AM",
            "dhuharTime": "01:31 PM",
            "asrTime": "05:32 PM",
            "maghribTime": "07:32 PM",
            "ishaTime": "08:52 PM",
            "qiyamTime": "02:14 AM",
            "isToday": 0,
            "fajarJamahTime": "6:30 AM",
            "zohrJamahTime": "2:00 PM",
            "asarJamahTime": "6:15 PM",
            "magribJamahTime": "7:37 PM",
            "ishaJamahTime": "9:15 PM"
        },
        {
            "responseCode": null,
            "responseDesc": null,
            "fajrHour": 5,
            "fajrMinute": 39,
            "dhuhrHour": 13,
            "dhuhrMinute": 31,
            "asrHour": 17,
            "asrMinute": 30,
            "maghribHour": 19,
            "maghribMinute": 29,
            "ishaHour": 20,
            "ishaMinute": 49,
            "qiyamHour": 2,
            "qiyamMinute": 15,
            "hijriDay": 9,
            "hijriMonth": 2,
            "hijriYear": 1442,
            "hijriDayOfWeek": 0,
            "hiriMonthName": "Safar",
            "hijriMonthNameEnglish": "Safar",
            "hijriDate": "9th Safar, 1442h",
            "sunriseHour": 0,
            "sunriseMinute": 0,
            "gregorianDate": 1601131800000,
            "gregorianDay": 26,
            "gregorianMonth": 8,
            "gregorianMonthName": "September",
            "gregorianMonthNameEnglish": "September",
            "gregorianYear": 2020,
            "gregorianDateString": "Sep 26, 2020",
            "dayOfWeek": "Sat",
            "nextPrayer": "lang.asr",
            "nextPrayerRemainingTime": "2:40:59",
            "nextPrayerRemainingTimeHours": 2,
            "nextPrayerRemainingTimeMinutes": 40,
            "nextPrayerRemainingTimeinDateFormat": 1598841600000,
            "currentPrayer": "lang.dhuhar",
            "currentPrayerPassedTime": "1 hour(s) 19 minute(s) ago",
            "currentPrayerPassedTimeHours": 1,
            "currentPrayerPassedTimeMinutes": 19,
            "islamicEvent": null,
            "fajarTime": "05:39 AM",
            "sunriseTime": "07:32 AM",
            "dhuharTime": "01:31 PM",
            "asrTime": "05:30 PM",
            "maghribTime": "07:29 PM",
            "ishaTime": "08:49 PM",
            "qiyamTime": "02:15 AM",
            "isToday": 0,
            "fajarJamahTime": "6:30 AM",
            "zohrJamahTime": "2:00 PM",
            "asarJamahTime": "6:15 PM",
            "magribJamahTime": "7:34 PM",
            "ishaJamahTime": "9:15 PM"
        },
        {
            "responseCode": null,
            "responseDesc": null,
            "fajrHour": 5,
            "fajrMinute": 41,
            "dhuhrHour": 13,
            "dhuhrMinute": 30,
            "asrHour": 17,
            "asrMinute": 28,
            "maghribHour": 19,
            "maghribMinute": 27,
            "ishaHour": 20,
            "ishaMinute": 47,
            "qiyamHour": 2,
            "qiyamMinute": 15,
            "hijriDay": 10,
            "hijriMonth": 2,
            "hijriYear": 1442,
            "hijriDayOfWeek": 0,
            "hiriMonthName": "Safar",
            "hijriMonthNameEnglish": "Safar",
            "hijriDate": "10th Safar, 1442h",
            "sunriseHour": 0,
            "sunriseMinute": 0,
            "gregorianDate": 1601218200000,
            "gregorianDay": 27,
            "gregorianMonth": 8,
            "gregorianMonthName": "September",
            "gregorianMonthNameEnglish": "September",
            "gregorianYear": 2020,
            "gregorianDateString": "Sep 27, 2020",
            "dayOfWeek": "Sun",
            "nextPrayer": "lang.asr",
            "nextPrayerRemainingTime": "2:38:59",
            "nextPrayerRemainingTimeHours": 2,
            "nextPrayerRemainingTimeMinutes": 38,
            "nextPrayerRemainingTimeinDateFormat": 1598841480000,
            "currentPrayer": "lang.dhuhar",
            "currentPrayerPassedTime": "1 hour(s) 20 minute(s) ago",
            "currentPrayerPassedTimeHours": 1,
            "currentPrayerPassedTimeMinutes": 20,
            "islamicEvent": null,
            "fajarTime": "05:41 AM",
            "sunriseTime": "07:33 AM",
            "dhuharTime": "01:30 PM",
            "asrTime": "05:28 PM",
            "maghribTime": "07:27 PM",
            "ishaTime": "08:47 PM",
            "qiyamTime": "02:15 AM",
            "isToday": 0,
            "fajarJamahTime": "6:30 AM",
            "zohrJamahTime": "2:00 PM",
            "asarJamahTime": "6:15 PM",
            "magribJamahTime": "7:32 PM",
            "ishaJamahTime": "9:15 PM"
        },
        {
            "responseCode": null,
            "responseDesc": null,
            "fajrHour": 5,
            "fajrMinute": 43,
            "dhuhrHour": 13,
            "dhuhrMinute": 30,
            "asrHour": 17,
            "asrMinute": 26,
            "maghribHour": 19,
            "maghribMinute": 25,
            "ishaHour": 20,
            "ishaMinute": 45,
            "qiyamHour": 2,
            "qiyamMinute": 17,
            "hijriDay": 11,
            "hijriMonth": 2,
            "hijriYear": 1442,
            "hijriDayOfWeek": 0,
            "hiriMonthName": "Safar",
            "hijriMonthNameEnglish": "Safar",
            "hijriDate": "11th Safar, 1442h",
            "sunriseHour": 0,
            "sunriseMinute": 0,
            "gregorianDate": 1601304600000,
            "gregorianDay": 28,
            "gregorianMonth": 8,
            "gregorianMonthName": "September",
            "gregorianMonthNameEnglish": "September",
            "gregorianYear": 2020,
            "gregorianDateString": "Sep 28, 2020",
            "dayOfWeek": "Mon",
            "nextPrayer": "lang.asr",
            "nextPrayerRemainingTime": "2:36:59",
            "nextPrayerRemainingTimeHours": 2,
            "nextPrayerRemainingTimeMinutes": 36,
            "nextPrayerRemainingTimeinDateFormat": 1598841360000,
            "currentPrayer": "lang.dhuhar",
            "currentPrayerPassedTime": "1 hour(s) 20 minute(s) ago",
            "currentPrayerPassedTimeHours": 1,
            "currentPrayerPassedTimeMinutes": 20,
            "islamicEvent": null,
            "fajarTime": "05:43 AM",
            "sunriseTime": "07:35 AM",
            "dhuharTime": "01:30 PM",
            "asrTime": "05:26 PM",
            "maghribTime": "07:25 PM",
            "ishaTime": "08:45 PM",
            "qiyamTime": "02:17 AM",
            "isToday": 0,
            "fajarJamahTime": "6:30 AM",
            "zohrJamahTime": "2:00 PM",
            "asarJamahTime": "6:15 PM",
            "magribJamahTime": "7:30 PM",
            "ishaJamahTime": "9:15 PM"
        },
        {
            "responseCode": null,
            "responseDesc": null,
            "fajrHour": 5,
            "fajrMinute": 45,
            "dhuhrHour": 13,
            "dhuhrMinute": 30,
            "asrHour": 17,
            "asrMinute": 24,
            "maghribHour": 19,
            "maghribMinute": 22,
            "ishaHour": 20,
            "ishaMinute": 42,
            "qiyamHour": 2,
            "qiyamMinute": 16,
            "hijriDay": 12,
            "hijriMonth": 2,
            "hijriYear": 1442,
            "hijriDayOfWeek": 0,
            "hiriMonthName": "Safar",
            "hijriMonthNameEnglish": "Safar",
            "hijriDate": "12th Safar, 1442h",
            "sunriseHour": 0,
            "sunriseMinute": 0,
            "gregorianDate": 1601391000000,
            "gregorianDay": 29,
            "gregorianMonth": 8,
            "gregorianMonthName": "September",
            "gregorianMonthNameEnglish": "September",
            "gregorianYear": 2020,
            "gregorianDateString": "Sep 29, 2020",
            "dayOfWeek": "Tue",
            "nextPrayer": "lang.asr",
            "nextPrayerRemainingTime": "2:34:59",
            "nextPrayerRemainingTimeHours": 2,
            "nextPrayerRemainingTimeMinutes": 34,
            "nextPrayerRemainingTimeinDateFormat": 1598841240000,
            "currentPrayer": "lang.dhuhar",
            "currentPrayerPassedTime": "1 hour(s) 20 minute(s) ago",
            "currentPrayerPassedTimeHours": 1,
            "currentPrayerPassedTimeMinutes": 20,
            "islamicEvent": null,
            "fajarTime": "05:45 AM",
            "sunriseTime": "07:37 AM",
            "dhuharTime": "01:30 PM",
            "asrTime": "05:24 PM",
            "maghribTime": "07:22 PM",
            "ishaTime": "08:42 PM",
            "qiyamTime": "02:16 AM",
            "isToday": 0,
            "fajarJamahTime": "6:30 AM",
            "zohrJamahTime": "2:00 PM",
            "asarJamahTime": "6:15 PM",
            "magribJamahTime": "7:27 PM",
            "ishaJamahTime": "9:15 PM"
        },
        {
            "responseCode": null,
            "responseDesc": null,
            "fajrHour": 5,
            "fajrMinute": 47,
            "dhuhrHour": 13,
            "dhuhrMinute": 29,
            "asrHour": 17,
            "asrMinute": 22,
            "maghribHour": 19,
            "maghribMinute": 20,
            "ishaHour": 20,
            "ishaMinute": 40,
            "qiyamHour": 2,
            "qiyamMinute": 18,
            "hijriDay": 13,
            "hijriMonth": 2,
            "hijriYear": 1442,
            "hijriDayOfWeek": 0,
            "hiriMonthName": "Safar",
            "hijriMonthNameEnglish": "Safar",
            "hijriDate": "13th Safar, 1442h",
            "sunriseHour": 0,
            "sunriseMinute": 0,
            "gregorianDate": 1601477400000,
            "gregorianDay": 30,
            "gregorianMonth": 8,
            "gregorianMonthName": "September",
            "gregorianMonthNameEnglish": "September",
            "gregorianYear": 2020,
            "gregorianDateString": "Sep 30, 2020",
            "dayOfWeek": "Wed",
            "nextPrayer": "lang.asr",
            "nextPrayerRemainingTime": "2:32:59",
            "nextPrayerRemainingTimeHours": 2,
            "nextPrayerRemainingTimeMinutes": 32,
            "nextPrayerRemainingTimeinDateFormat": 1598841120000,
            "currentPrayer": "lang.dhuhar",
            "currentPrayerPassedTime": "1 hour(s) 21 minute(s) ago",
            "currentPrayerPassedTimeHours": 1,
            "currentPrayerPassedTimeMinutes": 21,
            "islamicEvent": null,
            "fajarTime": "05:47 AM",
            "sunriseTime": "07:38 AM",
            "dhuharTime": "01:29 PM",
            "asrTime": "05:22 PM",
            "maghribTime": "07:20 PM",
            "ishaTime": "08:40 PM",
            "qiyamTime": "02:18 AM",
            "isToday": 0,
            "fajarJamahTime": "6:30 AM",
            "zohrJamahTime": "2:00 PM",
            "asarJamahTime": "6:15 PM",
            "magribJamahTime": "7:25 PM",
            "ishaJamahTime": "9:15 PM"
        }
    ],
    "monthName": "September 2020",
    "month": "September",
    "sencondaryMonthsInvolved": "Muharram 1442 - Safar 1442",
    "gregorianMonthName": null,
    "gregorianMonthInt": -1,
    "gregorianYearInt": -1,
    "hijriMonthName": "Muharram",
    "hijriMonthInt": -1,
    "hijriYearInt": -1,
    "secondMonthStartDate": 0,
    "secondaryMonthChangedate": 0,
    "secondaryMonthChangedateDescription": null,
    "firstMonthChangedate": 0,
    "firstMonthChangedateDescription": null,
    "currentDate": 0,
    "monthStartDate": 0,
    "firstMonth": "Muharram",
    "secondMonth": "Safar",
    "firstMonthYear": 1442,
    "secondMonthYear": 1442,
    "firstMonthStartDate": 1597968000000,
    "secondMonthYearStartDate": 1600473600000,
    "monthYearNameHijri": "Muharram 1442 - Safar 1442",
    "type": "Hijri"
}